pylandroid.py
setup.cfg
setup.py
pylandroid.egg-info/PKG-INFO
pylandroid.egg-info/SOURCES.txt
pylandroid.egg-info/dependency_links.txt
pylandroid.egg-info/requires.txt
pylandroid.egg-info/top_level.txt