Metadata-Version: 1.1
Name: pylandroid
Version: 0.0.1
Summary: A library to communicate with Worx Landroid robot mower
Home-page: https://github.com/freber/pylandroid
Author: Fredrik Silfver
Author-email: fredrik@above.se
License: MIT
Platform: UNKNOWN
Provides: pylandroid
